README.md
setup.cfg
setup.py
yj/__init__.py
yj/yj.py
yj_tool.egg-info/PKG-INFO
yj_tool.egg-info/SOURCES.txt
yj_tool.egg-info/dependency_links.txt
yj_tool.egg-info/entry_points.txt
yj_tool.egg-info/top_level.txt