Metadata-Version: 1.1
Name: yj-tool
Version: 1.1
Summary: A YAML to JSON convertor tool written in python.
Home-page: https://github.com/ankitjain28may/yj
Author: Ankit Jain
Author-email: ankitjain28may77@gmail.com
License: Apache-2.0 License
Keywords: yj,yaml-json,yaml convertor,yj-tool
Platform: UNKNOWN
Classifier: Development Status :: 3 - Alpha
Classifier: Environment :: Console
Classifier: Intended Audience :: Developers
Classifier: Intended Audience :: Information Technology
Classifier: Natural Language :: English
Classifier: Topic :: Software Development :: Build Tools
Classifier: License :: OSI Approved :: MIT License
Classifier: Programming Language :: Python :: 3
Classifier: Programming Language :: Python :: 3.6
Classifier: Programming Language :: Python :: 3.7
